ros_rosidl_typesupport_c-3.3.3.data/data/include/rosidl_typesupport_c/rosidl_typesupport_c/identifier.h
ros_rosidl_typesupport_c-3.3.3.data/data/include/rosidl_typesupport_c/rosidl_typesupport_c/message_type_support_dispatch.h
ros_rosidl_typesupport_c-3.3.3.data/data/include/rosidl_typesupport_c/rosidl_typesupport_c/service_type_support_dispatch.h
ros_rosidl_typesupport_c-3.3.3.data/data/include/rosidl_typesupport_c/rosidl_typesupport_c/type_support_map.h
ros_rosidl_typesupport_c-3.3.3.data/data/include/rosidl_typesupport_c/rosidl_typesupport_c/visibility_control.h
ros_rosidl_typesupport_c-3.3.3.data/data/lib/librosidl_typesupport_c.so
ros_rosidl_typesupport_c-3.3.3.data/data/lib/python3.13/site-packages/rosidl_typesupport_c/__init__.py
ros_rosidl_typesupport_c-3.3.3.data/data/lib/python3.13/site-packages/rosidl_typesupport_c/cli.py
ros_rosidl_typesupport_c-3.3.3.data/data/lib/python3.13/site-packages/rosidl_typesupport_c/__pycache__/__init__.cpython-313.pyc
ros_rosidl_typesupport_c-3.3.3.data/data/lib/python3.13/site-packages/rosidl_typesupport_c/__pycache__/cli.cpython-313.pyc
ros_rosidl_typesupport_c-3.3.3.data/data/lib/python3.13/site-packages/rosidl_typesupport_c-3.3.3-py3.13.egg-info/PKG-INFO
ros_rosidl_typesupport_c-3.3.3.data/data/lib/python3.13/site-packages/rosidl_typesupport_c-3.3.3-py3.13.egg-info/SOURCES.txt
ros_rosidl_typesupport_c-3.3.3.data/data/lib/python3.13/site-packages/rosidl_typesupport_c-3.3.3-py3.13.egg-info/dependency_links.txt
ros_rosidl_typesupport_c-3.3.3.data/data/lib/python3.13/site-packages/rosidl_typesupport_c-3.3.3-py3.13.egg-info/entry_points.txt
ros_rosidl_typesupport_c-3.3.3.data/data/lib/python3.13/site-packages/rosidl_typesupport_c-3.3.3-py3.13.egg-info/top_level.txt
ros_rosidl_typesupport_c-3.3.3.data/data/lib/rosidl_typesupport_c/rosidl_typesupport_c
ros_rosidl_typesupport_c-3.3.3.data/data/share/ament_index/resource_index/package_run_dependencies/rosidl_typesupport_c
ros_rosidl_typesupport_c-3.3.3.data/data/share/ament_index/resource_index/packages/rosidl_typesupport_c
ros_rosidl_typesupport_c-3.3.3.data/data/share/ament_index/resource_index/parent_prefix_path/rosidl_typesupport_c
ros_rosidl_typesupport_c-3.3.3.data/data/share/ament_index/resource_index/rosidl_runtime_packages/rosidl_typesupport_c
ros_rosidl_typesupport_c-3.3.3.data/data/share/rosidl_typesupport_c/local_setup.bash
ros_rosidl_typesupport_c-3.3.3.data/data/share/rosidl_typesupport_c/local_setup.dsv
ros_rosidl_typesupport_c-3.3.3.data/data/share/rosidl_typesupport_c/local_setup.sh
ros_rosidl_typesupport_c-3.3.3.data/data/share/rosidl_typesupport_c/local_setup.zsh
ros_rosidl_typesupport_c-3.3.3.dist-info/METADATA
ros_rosidl_typesupport_c-3.3.3.dist-info/WHEEL
ros_rosidl_typesupport_c-3.3.3.dist-info/entry_points.txt
ros_rosidl_typesupport_c-3.3.3.dist-info/top_level.txt
ros_rosidl_typesupport_c-3.3.3.dist-info/RECORD
